pyspanner/__init__.py
pyspanner/flaskapi_utils.py
pyspanner/kafka_utils.py
pyspanner/log_utils.py
pyspanner/mongo_utils.py
pyspanner/redis_utils.py
pyspanner/sched_utils.py
pyspanner/singleton_utils.py
pyspanner/str_utils.py
pyspanner/yaml_utils.py
pyspanner-0.0.1.dist-info/LICENSE
pyspanner-0.0.1.dist-info/METADATA
pyspanner-0.0.1.dist-info/WHEEL
pyspanner-0.0.1.dist-info/top_level.txt
pyspanner-0.0.1.dist-info/RECORD
